Metadata-Version: 2.1
Name: lab-serializer
Version: 1.4
Summary: JSON/XML serializer
Home-page: UNKNOWN
Author: L1h1
License: UNKNOWN
Platform: UNKNOWN
